<?xml version="1.0" encoding="UTF-8" ?>
<!DOCTYPE mapper PUBLIC "-//mybatis.org//DTD Mapper 3.0//EN" "http://mybatis.org/dtd/mybatis-3-mapper.dtd" >
<mapper namespace="basedata.guardAreaDao" >
  <resultMap id="BaseResultMap" type="com.ziroom.minsu.entity.conf.GuardAreaEntity" >
    <!--
      WARNING - @mbggenerated
      This element is automatically generated by MyBatis Generator, do not modify.
      This element was generated on Tue Jul 05 14:51:00 CST 2016.
    -->
    <id column="id" property="id" jdbcType="INTEGER" />
    <result column="fid" property="fid" jdbcType="VARCHAR" />
    <result column="nation_code" property="nationCode" jdbcType="VARCHAR" />
    <result column="province_code" property="provinceCode" jdbcType="VARCHAR" />
    <result column="city_code" property="cityCode" jdbcType="VARCHAR" />
    <result column="area_code" property="areaCode" jdbcType="VARCHAR" />
    <result column="emp_code" property="empCode" jdbcType="VARCHAR" />
    <result column="emp_phone" property="empPhone" jdbcType="VARCHAR" />
    <result column="emp_name" property="empName" jdbcType="VARCHAR" />
    <result column="create_fid" property="createFid" jdbcType="VARCHAR" />
    <result column="create_date" property="createDate" jdbcType="TIMESTAMP" />
    <result column="last_modify_date" property="lastModifyDate" jdbcType="TIMESTAMP" />
    <result column="is_del" property="isDel" jdbcType="INTEGER" />
  </resultMap>

  <sql id="Base_Column_List" >
    <!--
      WARNING - @mbggenerated
      This element is automatically generated by MyBatis Generator, do not modify.
      This element was generated on Tue Jul 05 14:51:00 CST 2016.
    -->
    id, fid, nation_code, province_code, city_code, area_code, emp_code, emp_phone, emp_name, 
    create_fid, create_date, last_modify_date, is_del
  </sql>
 
  <select id="selectByPrimaryKey" resultMap="BaseResultMap" parameterType="java.lang.Integer" >
    <!--
      WARNING - @mbggenerated
      This element is automatically generated by MyBatis Generator, do not modify.
      This element was generated on Tue Jul 05 14:51:00 CST 2016.
    -->
    select 
    <include refid="Base_Column_List" />
    from t_guard_area
    where id = #{id,jdbcType=INTEGER}
  </select>
  <select id="selectByPhy" resultMap="BaseResultMap" parameterType="map" >
    SELECT <include refid="Base_Column_List" />
    FROM t_guard_area tga
	WHERE tga.nation_code=#{nationCode,jdbcType=VARCHAR}
	AND tga.province_code=#{provinceCode,jdbcType=VARCHAR}
	AND tga.city_code=#{cityCode,jdbcType=VARCHAR}
	AND tga.area_code=#{areaCode,jdbcType=VARCHAR}
	AND tga.is_del=0
   </select>
   
    <select id="findGuardAreaByFid" resultMap="BaseResultMap" parameterType="java.lang.String" >
    <!--
      WARNING - @mbggenerated
      This element is automatically generated by MyBatis Generator, do not modify.
      This element was generated on Tue Jul 05 14:51:00 CST 2016.
    -->
    select 
    <include refid="Base_Column_List" />
    from t_guard_area
    where fid = #{fid,jdbcType=VARCHAR}
  </select>
    <select id="findGaurdAreaByPage" resultMap="BaseResultMap" parameterType="com.ziroom.minsu.services.basedata.dto.GuardAreaRequest" >
    <!--   条件分页查询 -->
    select 
    <include refid="Base_Column_List" />
    from t_guard_area
    where 1=1 
    <if test="nationCode != null and nationCode !=''" >
     AND nation_code = #{nationCode,jdbcType=VARCHAR}
    </if>
    <if test="provinceCode != null and provinceCode !=''" >
    AND  province_code = #{provinceCode,jdbcType=VARCHAR}
    </if>
    <if test="cityCode != null and cityCode !=''" >
    AND  city_code = #{cityCode,jdbcType=VARCHAR}
    </if>
    <if test="areaCode != null and areaCode !=''" >
    AND  area_code = #{areaCode,jdbcType=VARCHAR}
    </if>
    <if test="empCode != null and empCode != ''" >
     AND emp_code = #{empCode,jdbcType=VARCHAR}
    </if>
    <if test="empPhone != null and empPhone !=''" >
    AND  emp_phone = #{empPhone,jdbcType=VARCHAR}
    </if>
    <if test="empName != null and empName !=''" >
    AND  emp_name = #{empName,jdbcType=VARCHAR}
    </if>
    <if test="createFid != null and createFid !=''" >
    AND   create_fid = #{createFid,jdbcType=VARCHAR}
    </if>
    <if test="isDel != null" >
    AND  is_del = #{isDel,jdbcType=INTEGER}
    </if>
    ORDER BY create_date DESC
  </select>
  
   <select id="findGaurdAreaByCondition" resultMap="BaseResultMap" parameterType="com.ziroom.minsu.services.basedata.dto.GuardAreaRequest" >
    <!--   条件分页查询 -->
    select 
    <include refid="Base_Column_List" />
    from t_guard_area
    where 1=1 
    <if test="nationCode != null and nationCode !=''" >
     AND nation_code = #{nationCode,jdbcType=VARCHAR}
    </if>
    <if test="provinceCode != null and provinceCode !=''" >
    AND  province_code = #{provinceCode,jdbcType=VARCHAR}
    </if>
    <if test="cityCode != null and cityCode !=''" >
    AND  city_code = #{cityCode,jdbcType=VARCHAR}
    </if>
    <if test="areaCode != null and areaCode !=''" >
    AND  area_code = #{areaCode,jdbcType=VARCHAR}
    </if>
    <if test="empCode != null and empCode != ''" >
     AND emp_code = #{empCode,jdbcType=VARCHAR}
    </if>
    <if test="empPhone != null and empPhone !=''" >
    AND  emp_phone = #{empPhone,jdbcType=VARCHAR}
    </if>
    <if test="empName != null and empName !=''" >
    AND  emp_name = #{empName,jdbcType=VARCHAR}
    </if>
    <if test="createFid != null and createFid !=''" >
    AND   create_fid = #{createFid,jdbcType=VARCHAR}
    </if>
    <if test="isDel != null" >
    AND  is_del = #{isDel,jdbcType=INTEGER}
    </if>
    ORDER BY last_modify_date 
  </select>
  
  <delete id="deleteByPrimaryKey" parameterType="java.lang.Integer" >
    <!--
      WARNING - @mbggenerated
      This element is automatically generated by MyBatis Generator, do not modify.
      This element was generated on Tue Jul 05 14:51:00 CST 2016.
    -->
    delete from t_guard_area
    where id = #{id,jdbcType=INTEGER}
  </delete>
  
  <insert id="insert" parameterType="com.ziroom.minsu.entity.conf.GuardAreaEntity" >
    <!--
      WARNING - @mbggenerated
      This element is automatically generated by MyBatis Generator, do not modify.
      This element was generated on Tue Jul 05 14:51:00 CST 2016.
    -->
    insert into t_guard_area (id, fid, nation_code, 
      province_code, city_code, area_code, 
      emp_code, emp_phone, emp_name, 
      create_fid, create_date, last_modify_date, 
      is_del)
    values (#{id,jdbcType=INTEGER}, #{fid,jdbcType=VARCHAR}, #{nationCode,jdbcType=VARCHAR}, 
      #{provinceCode,jdbcType=VARCHAR}, #{cityCode,jdbcType=VARCHAR}, #{areaCode,jdbcType=VARCHAR}, 
      #{empCode,jdbcType=VARCHAR}, #{empPhone,jdbcType=VARCHAR}, #{empName,jdbcType=VARCHAR}, 
      #{createFid,jdbcType=VARCHAR}, #{createDate,jdbcType=TIMESTAMP}, #{lastModifyDate,jdbcType=TIMESTAMP}, 
      #{isDel,jdbcType=INTEGER})
  </insert>
  <insert id="insertSelective" parameterType="com.ziroom.minsu.entity.conf.GuardAreaEntity" >
    <!--
      WARNING - @mbggenerated
      This element is automatically generated by MyBatis Generator, do not modify.
      This element was generated on Tue Jul 05 14:51:00 CST 2016.
    -->
    insert into t_guard_area
    <trim prefix="(" suffix=")" suffixOverrides="," >
      <if test="id != null" >
        id,
      </if>
      <if test="fid != null" >
        fid,
      </if>
      <if test="nationCode != null" >
        nation_code,
      </if>
      <if test="provinceCode != null" >
        province_code,
      </if>
      <if test="cityCode != null" >
        city_code,
      </if>
      <if test="areaCode != null" >
        area_code,
      </if>
      <if test="empCode != null" >
        emp_code,
      </if>
      <if test="empPhone != null" >
        emp_phone,
      </if>
      <if test="empName != null" >
        emp_name,
      </if>
      <if test="createFid != null" >
        create_fid,
      </if>
      <if test="createDate != null" >
        create_date,
      </if>
      <if test="lastModifyDate != null" >
        last_modify_date,
      </if>
      <if test="isDel != null" >
        is_del,
      </if>
    </trim>
    <trim prefix="values (" suffix=")" suffixOverrides="," >
      <if test="id != null" >
        #{id,jdbcType=INTEGER},
      </if>
      <if test="fid != null" >
        #{fid,jdbcType=VARCHAR},
      </if>
      <if test="nationCode != null" >
        #{nationCode,jdbcType=VARCHAR},
      </if>
      <if test="provinceCode != null" >
        #{provinceCode,jdbcType=VARCHAR},
      </if>
      <if test="cityCode != null" >
        #{cityCode,jdbcType=VARCHAR},
      </if>
      <if test="areaCode != null" >
        #{areaCode,jdbcType=VARCHAR},
      </if>
      <if test="empCode != null" >
        #{empCode,jdbcType=VARCHAR},
      </if>
      <if test="empPhone != null" >
        #{empPhone,jdbcType=VARCHAR},
      </if>
      <if test="empName != null" >
        #{empName,jdbcType=VARCHAR},
      </if>
      <if test="createFid != null" >
        #{createFid,jdbcType=VARCHAR},
      </if>
      <if test="createDate != null" >
        #{createDate,jdbcType=TIMESTAMP},
      </if>
      <if test="lastModifyDate != null" >
        #{lastModifyDate,jdbcType=TIMESTAMP},
      </if>
      <if test="isDel != null" >
        #{isDel,jdbcType=INTEGER},
      </if>
    </trim>
  </insert>

  <update id="updateByPrimaryKeySelective" parameterType="com.ziroom.minsu.entity.conf.GuardAreaEntity" >
    <!--
      WARNING - @mbggenerated
      This element is automatically generated by MyBatis Generator, do not modify.
      This element was generated on Tue Jul 05 14:51:00 CST 2016.
    -->
    update t_guard_area
    <set >
      <if test="fid != null" >
        fid = #{fid,jdbcType=VARCHAR},
      </if>
      <if test="nationCode != null" >
        nation_code = #{nationCode,jdbcType=VARCHAR},
      </if>
      <if test="provinceCode != null" >
        province_code = #{provinceCode,jdbcType=VARCHAR},
      </if>
      <if test="cityCode != null" >
        city_code = #{cityCode,jdbcType=VARCHAR},
      </if>
      <if test="areaCode != null" >
        area_code = #{areaCode,jdbcType=VARCHAR},
      </if>
      <if test="empCode != null" >
        emp_code = #{empCode,jdbcType=VARCHAR},
      </if>
      <if test="empPhone != null" >
        emp_phone = #{empPhone,jdbcType=VARCHAR},
      </if>
      <if test="empName != null" >
        emp_name = #{empName,jdbcType=VARCHAR},
      </if>
      <if test="createFid != null" >
        create_fid = #{createFid,jdbcType=VARCHAR},
      </if>
      <if test="createDate != null" >
        create_date = #{createDate,jdbcType=TIMESTAMP},
      </if>
      <if test="lastModifyDate != null" >
        last_modify_date = #{lastModifyDate,jdbcType=TIMESTAMP},
      </if>
      <if test="isDel != null" >
        is_del = #{isDel,jdbcType=INTEGER},
      </if>
    </set>
    where id = #{id,jdbcType=INTEGER}
  </update>
  <update id="updateByPrimaryKey" parameterType="com.ziroom.minsu.entity.conf.GuardAreaEntity" >
    <!--
      WARNING - @mbggenerated
      This element is automatically generated by MyBatis Generator, do not modify.
      This element was generated on Tue Jul 05 14:51:00 CST 2016.
    -->
    update t_guard_area
    set fid = #{fid,jdbcType=VARCHAR},
      nation_code = #{nationCode,jdbcType=VARCHAR},
      province_code = #{provinceCode,jdbcType=VARCHAR},
      city_code = #{cityCode,jdbcType=VARCHAR},
      area_code = #{areaCode,jdbcType=VARCHAR},
      emp_code = #{empCode,jdbcType=VARCHAR},
      emp_phone = #{empPhone,jdbcType=VARCHAR},
      emp_name = #{empName,jdbcType=VARCHAR},
      create_fid = #{createFid,jdbcType=VARCHAR},
      create_date = #{createDate,jdbcType=TIMESTAMP},
      last_modify_date = #{lastModifyDate,jdbcType=TIMESTAMP},
      is_del = #{isDel,jdbcType=INTEGER}
    where id = #{id,jdbcType=INTEGER}
  </update>
  
    <update id="updateGuardAreaByFid" parameterType="com.ziroom.minsu.entity.conf.GuardAreaEntity" >
    <!--   update entity by fid -->
    update t_guard_area
    <set >
      <if test="nationCode != null and nationCode!=''" >
        nation_code = #{nationCode,jdbcType=VARCHAR},
      </if>
      <if test="provinceCode != null and provinceCode!=''" >
        province_code = #{provinceCode,jdbcType=VARCHAR},
      </if>
      <if test="cityCode != null and cityCode !='' " >
        city_code = #{cityCode,jdbcType=VARCHAR},
      </if>
      <if test="areaCode != null and areaCode !=''" >
        area_code = #{areaCode,jdbcType=VARCHAR},
      </if>
      <if test="empCode != null and empCode !=''" >
        emp_code = #{empCode,jdbcType=VARCHAR},
      </if>
      <if test="empPhone != null and empPhone !=''" >
        emp_phone = #{empPhone,jdbcType=VARCHAR},
      </if>
      <if test="empName != null and empName !=''" >
        emp_name = #{empName,jdbcType=VARCHAR},
      </if>
      <if test="createFid != null and createFid !=''" >
        create_fid = #{createFid,jdbcType=VARCHAR},
      </if>
      <if test="createDate != null" >
        create_date = #{createDate,jdbcType=TIMESTAMP},
      </if>
      <if test="lastModifyDate != null" >
        last_modify_date = #{lastModifyDate,jdbcType=TIMESTAMP},
      </if>
      <if test="isDel != null" >
        is_del = #{isDel,jdbcType=INTEGER},
      </if>
    </set>
    where fid = #{fid,jdbcType=VARCHAR}
  </update>
</mapper>